file_diff_analyzer/__init__.py
file_diff_analyzer/file_diff_analyzer.py
file_diff_analyzer-0.1.1.dist-info/licenses/LICENSE
file_diff_analyzer-0.1.1.dist-info/METADATA
file_diff_analyzer-0.1.1.dist-info/WHEEL
file_diff_analyzer-0.1.1.dist-info/top_level.txt
file_diff_analyzer-0.1.1.dist-info/RECORD
