Metadata-Version: 2.4
Name: file-diff-analyzer
Version: 0.1.1
Summary: Analyze function-level code differences between two versions of a file
Author-email: Abdul Rehman <arehman8125@gmail.com>
License: MIT License
Requires-Python: >=3.8
License-File: LICENSE
Dynamic: license-file
